dicewarepy/__init__.py
dicewarepy/diceware.py
dicewarepy/wordlists/de-7776-v1-diceware.txt
dicewarepy/wordlists/eff_large_wordlist.txt
dicewarepy-2025.5.1.dist-info/licenses/LICENSE
dicewarepy-2025.5.1.dist-info/METADATA
dicewarepy-2025.5.1.dist-info/WHEEL
dicewarepy-2025.5.1.dist-info/top_level.txt
dicewarepy-2025.5.1.dist-info/RECORD
