Metadata-Version: 2.4
Name: dicewarepy
Version: 2025.5.1
Summary: Minimalist Python library designed for the random selection of words from cryptographic wordlists, utilizing the Diceware method.
Author: inwerk
License-Expression: MIT
Keywords: dicewarepy,diceware,dice,die,wordlist,wordlists,passphrase,passphrases,password,passwords,security
Classifier: Development Status :: 5 - Production/Stable
Classifier: Intended Audience :: Education
Classifier: Intended Audience :: Developers
Classifier: Programming Language :: Python :: 3
Classifier: Programming Language :: Python :: 3.11
Classifier: Programming Language :: Python :: 3.12
Classifier: Programming Language :: Python :: 3.13
Classifier: Topic :: Utilities
Classifier: Topic :: Security
Classifier: Topic :: Security :: Cryptography
Requires-Python: >=3.11
License-File: LICENSE
Dynamic: license-file
